smartpaste/__init__.py
smartpaste/__main__.py
smartpaste/main.py
smartpaste/handlers/__init__.py
smartpaste/handlers/code.py
smartpaste/handlers/email.py
smartpaste/handlers/image.py
smartpaste/handlers/math.py
smartpaste/handlers/number.py
smartpaste/handlers/text.py
smartpaste/handlers/url.py
smartpaste/utils/__init__.py
smartpaste/utils/io.py
smartpaste/utils/nlp.py
smartpaste/utils/timebox.py
smartpaste_ai-1.0.0.dist-info/METADATA
smartpaste_ai-1.0.0.dist-info/WHEEL
smartpaste_ai-1.0.0.dist-info/entry_points.txt
smartpaste_ai-1.0.0.dist-info/licenses/LICENSE
smartpaste_ai-1.0.0.dist-info/RECORD
