Metadata-Version: 2.4
Name: smartpaste-ai
Version: 1.0.0
Summary: A context-aware AI clipboard assistant that enriches content and saves organized markdown files
Project-URL: Homepage, https://github.com/AbdHajjar/smartpaste
Project-URL: Repository, https://github.com/AbdHajjar/smartpaste
Project-URL: Issues, https://github.com/AbdHajjar/smartpaste/issues
Author: SmartPaste Contributors
License-Expression: MIT
License-File: LICENSE
Keywords: ai,automation,clipboard,markdown,productivity
Classifier: Development Status :: 3 - Alpha
Classifier: Intended Audience :: End Users/Desktop
Classifier: License :: OSI Approved :: MIT License
Classifier: Operating System :: OS Independent
Classifier: Programming Language :: Python :: 3
Classifier: Programming Language :: Python :: 3.10
Classifier: Programming Language :: Python :: 3.11
Classifier: Programming Language :: Python :: 3.12
Classifier: Topic :: Office/Business
Classifier: Topic :: Text Processing :: Markup :: Markdown
Classifier: Topic :: Utilities
Requires-Python: >=3.10
Requires-Dist: beautifulsoup4>=4.12.0
Requires-Dist: click>=8.1.0
Requires-Dist: langdetect>=1.0.9
Requires-Dist: lxml>=4.9.0
Requires-Dist: numpy>=1.24.0
Requires-Dist: pillow>=10.0.0
Requires-Dist: pyperclip>=1.8.2
Requires-Dist: pyyaml>=6.0.1
Requires-Dist: readability-lxml>=0.8.1
Requires-Dist: requests>=2.31.0
Requires-Dist: scikit-learn>=1.3.0
Requires-Dist: sentence-transformers>=2.2.2
Provides-Extra: dev
Requires-Dist: black>=23.7.0; extra == 'dev'
Requires-Dist: flake8>=6.0.0; extra == 'dev'
Requires-Dist: mypy>=1.5.0; extra == 'dev'
Requires-Dist: pre-commit>=3.3.0; extra == 'dev'
Requires-Dist: pytest-cov>=4.1.0; extra == 'dev'
Requires-Dist: pytest>=7.4.0; extra == 'dev'
Provides-Extra: ocr
Requires-Dist: pytesseract>=0.3.10; extra == 'ocr'
